LICENSE
MANIFEST.in
README.md
requirements.txt
setup.py
pySURF.egg-info/PKG-INFO
pySURF.egg-info/SOURCES.txt
pySURF.egg-info/dependency_links.txt
pySURF.egg-info/not-zip-safe
pySURF.egg-info/requires.txt
pySURF.egg-info/top_level.txt
surf/NN.py
surf/__init__.py
surf/_version.py
surf/rf.py
surf/spatialModel.py
surf/utils.py