Metadata-Version: 2.1
Name: pySURF
Version: 0.2.4.3
Summary: Spatial Uncertainty Research Framework
Home-page: https://github.com/NHERI-SimCenter/SURF
Author: Charles Wang
Author-email: c_w@berkeley.edu
License: BSD 3-Clause
Keywords: pySURF,random field,spatial uncertainty,surf,surf library,surf framework
Platform: UNKNOWN
Classifier: Intended Audience :: Developers
Classifier: License :: OSI Approved :: BSD License
Classifier: Natural Language :: English
Classifier: Programming Language :: Python :: 3.4
Classifier: Programming Language :: Python :: 3.5
Classifier: Programming Language :: Python :: 3.6
Requires-Python: >=3.0
